{
    "title": "g.Raphaël",
    "output": "../g.raphael/docs/reference.html",
    "scripts": ["../raphael-min.js", "../g.raphael.js", "../g.line.js", "../g.dot.js", "../g.bar.js", "../g.pie.js", "reference.js"],
    "files": [{
        "url": "../g.raphael/g.raphael.js",
        "link": "https://github.com/DmitryBaranovskiy/g.raphael/blob/master/g.raphael.js"
    },{
        "url": "../g.raphael/g.line.js",
        "link": "https://github.com/DmitryBaranovskiy/g.raphael/blob/master/g.line.js"
    },{
        "url": "../g.raphael/g.dot.js",
        "link": "https://github.com/DmitryBaranovskiy/g.raphael/blob/master/g.dot.js"
    },{
        "url": "../g.raphael/g.bar.js",
        "link": "https://github.com/DmitryBaranovskiy/g.raphael/blob/master/g.bar.js"
    },{
        "url": "../g.raphael/g.pie.js",
        "link": "https://github.com/DmitryBaranovskiy/g.raphael/blob/master/g.pie.js"
    }]
}
